{
  "name": "XY0",
  "description": "Synced from controller: XY0",
  "commands": [
    "{'name': 'XY0', 'category': 'Macros', 'description': '', 'path': 'Home/Macros/XY0.ngc', 'modified': '2025-06-24T17:32:02Z', 'size': 87, '__module__': 'core.communication', '__dict__': <attribute '__dict__' of 'Macro' objects>, '__weakref__': <attribute '__weakref__' of 'Macro' objects>, '__doc__': None}"
  ],
  "created_date": "2025-08-13T08:40:58.684474",
  "modified_date": "2025-08-13T09:50:41.557053",
  "category": "system",
  "color": "#e6e6e6",
  "hotkey": ""
}